nia_ai_api_client/__init__.py
nia_ai_api_client/api/__init__.py
nia_ai_api_client/api/context_sharing/__init__.py
nia_ai_api_client/api/context_sharing/delete_context.py
nia_ai_api_client/api/context_sharing/get_context.py
nia_ai_api_client/api/context_sharing/list_contexts.py
nia_ai_api_client/api/context_sharing/save_context.py
nia_ai_api_client/api/context_sharing/search_contexts.py
nia_ai_api_client/api/context_sharing/semantic_search_contexts.py
nia_ai_api_client/api/context_sharing/update_context.py
nia_ai_api_client/api/data_sources/__init__.py
nia_ai_api_client/api/data_sources/create_data_source.py
nia_ai_api_client/api/data_sources/delete_data_source.py
nia_ai_api_client/api/data_sources/get_data_source.py
nia_ai_api_client/api/data_sources/get_data_source_content.py
nia_ai_api_client/api/data_sources/get_documentation_tree.py
nia_ai_api_client/api/data_sources/grep_documentation.py
nia_ai_api_client/api/data_sources/list_data_sources.py
nia_ai_api_client/api/data_sources/list_documentation_directory.py
nia_ai_api_client/api/data_sources/read_documentation_page.py
nia_ai_api_client/api/data_sources/rename_data_source.py
nia_ai_api_client/api/oracle_research/__init__.py
nia_ai_api_client/api/oracle_research/cancel_oracle_job.py
nia_ai_api_client/api/oracle_research/create_oracle_job.py
nia_ai_api_client/api/oracle_research/get_oracle_job.py
nia_ai_api_client/api/oracle_research/get_oracle_session_detail.py
nia_ai_api_client/api/oracle_research/get_oracle_session_messages.py
nia_ai_api_client/api/oracle_research/list_oracle_jobs.py
nia_ai_api_client/api/oracle_research/list_oracle_sessions.py
nia_ai_api_client/api/oracle_research/oracle_research.py
nia_ai_api_client/api/oracle_research/oracle_research_stream.py
nia_ai_api_client/api/oracle_research/stream_oracle_job.py
nia_ai_api_client/api/oracle_research/stream_oracle_session_chat.py
nia_ai_api_client/api/package_search/__init__.py
nia_ai_api_client/api/package_search/package_search_grep.py
nia_ai_api_client-1.0.2.dist-info/METADATA
nia_ai_api_client-1.0.2.dist-info/WHEEL
nia_ai_api_client-1.0.2.dist-info/RECORD
